LICENSE
MANIFEST.in
README.rst
setup.py
yanc/__init__.py
yanc/colorstream.py
yanc/test_yanc.py
yanc/yancplugin.py
yanc.egg-info/PKG-INFO
yanc.egg-info/SOURCES.txt
yanc.egg-info/dependency_links.txt
yanc.egg-info/entry_points.txt
yanc.egg-info/top_level.txt